Workbook

Sheet Assumptions
A1: Small-Batch Coffee Roasting — Assumptions
A3: Yellow cells = your inputs. Change these; every other tab recalculates automatically.
A5: 1. Product, Packaging & Green Bean Sourcing
A6: Item | B6: Value | C6: Unit | D6: Notes
A7: Standard bag size | B7: 250 | C7: grams | D7: Most home-run specialty roasters standardize on 250g retail bags
A8: Green bean cost (FOB / farm-gate) | B8: 550 | C8: ₹/kg | D8: PLACEHOLDER — your actual origin/estate/importer quote
A9: Freight, customs duty & sourcing logistics | B9: 60 | C9: ₹/kg | D9: Landed-cost add-on: inbound freight, import duty (if importing), local transport to your apartment
A10: Roast loss (weight lost while roasting) | B10: 0.15 | C10: % | D10: Typical range 12-18% for light-medium roast; higher for dark roast
A11: Packaging cost (pouch + valve + label) | B11: 25 | C11: ₹/bag | D11: Kraft pouch with degassing valve + printed label, small-batch pricing
A12: Sealing/consumables (tape, stickers, tags) | B12: 5 | C12: ₹/bag | D12: Small per-unit miscellaneous cost
A14: 2. Selling Price & Channel
A15: Item | B15: Value | C15: Unit | D15: Notes
A16: Retail selling price per bag | B16: 450 | C16: ₹/bag | D16: PLACEHOLDER — street price for specialty single-origin 250g; set to your positioning
A17: Blended platform/marketplace commission | B17: 0.15 | C17: % | D17: Weighted avg across own site, Instagram/WhatsApp DTC, and marketplaces
A18: Payment gateway fee | B18: 0.02 | C18: % | D18: Razorpay/PayU etc., applied on realised price
A19: Shipping cost per bag (you pay courier) | B19: 45 | C19: ₹/bag | D19: Set to 0 if fully passed through to customer
A20: Shipping charged to customer per bag | B20: 45 | C20: ₹/bag | D20: Set equal to cost if you charge shipping at par
A22: 3. Equipment & Setup (One-Time)
A23: Item | B23: Cost (₹) | C23: Useful Life (yrs) | D23: Monthly Depreciation (₹)
A24: Mini-batch roaster (1-2 kg batch capacity) | B24: 175000 | C24: 5 | D24: =B24/(C24*12) -> 2916.6667
A25: Other equipment (weighing scale, sealer, moisture meter, storage bins, cupping gear) | B25: 45000 | C25: 5 | D25: =B25/(C25*12) -> 750
A26: Total monthly depreciation | D26: =SUM(D24:D25) -> 3666.6667
A27: Depreciation spreads your one-time roaster/equipment spend across its useful life so unit economics reflect the real monthly cost of owning it, not just cash-in-hand.
A29: 4. Fixed / Overhead Costs (Monthly)
A30: Item | B30: Value | C30: Unit | D30: Notes
A31: Owner's salary draw | B31: 100000 | C31: ₹/mo | D31: Equals ₹12L / 12
A32: Business development spend | B32: 16667 | C32: ₹/mo | D32: Equals ₹2L / 12 — marketing, samples-for-customers, travel, cuppings
A33: Green bean sourcing overhead (origin trips, sample orders, courier for green sample lots) | B33: 5000 | C33: ₹/mo | D33: Separate from freight/duty in Section 1, which sits inside COGS — this is exploratory sourcing spend, not tied to a specific batch
A34: Roaster fuel/electricity (incremental) | B34: 4000 | C34: ₹/mo | D34: Gas or electric roaster running cost on top of normal apartment bill
A35: Packaging/design tooling amortised | B35: 1500 | C35: ₹/mo | D35: Label printing setup, die-cuts etc., spread monthly
A36: Software/subscriptions | B36: 2000 | C36: ₹/mo | D36: Website, invoicing, inventory tools
A37: Misc/contingency | B37: 3000 | C37: ₹/mo | D37: Buffer for small leakages running ops out of an apartment
A38: Equipment depreciation (roaster + other gear) | B38: =D26 -> 3666.6667 | C38: ₹/mo | D38: Linked from Section 3 — the monthly cost of owning your roaster
A40: Total Fixed Cost / month | B40: =SUM(B31:B38) -> 135833.67
A41: Total Fixed Cost / year | B41: =B40*12 -> 1630004

Sheet Unit Economics
A1: Unit Economics — Per 250g Bag
A3: All figures flow from Assumptions tab. Nothing here is hardcoded.
A5: Revenue Realisation
A6: Item | B6: ₹ / bag
A7: Retail selling price | B7: =Assumptions!B16 -> 450
A8: Less: Platform/marketplace commission | B8: =-Assumptions!B16*Assumptions!B17 -> -67.5
A9: Less: Payment gateway fee | B9: =-Assumptions!B16*Assumptions!B18 -> -9
A10: Add: Shipping collected from customer | B10: =Assumptions!B20 -> 45
A11: Less: Shipping cost paid to courier | B11: =-Assumptions!B19 -> -45
A12: Net Realisation per bag | B12: =SUM(B7:B11) -> 373.5
A14: Cost of Goods Sold (COGS)
A15: Item | B15: ₹ / bag
A16: Green bean input required (accounting for roast loss) | B16: =(Assumptions!B7/1000)/(1-Assumptions!B10) -> 0.29411765
A17: Landed green bean cost per bag (bean + freight/duty) | B17: =B16*(Assumptions!B8+Assumptions!B9) -> 179.41176
A18: Packaging cost (pouch+valve+label) | B18: =Assumptions!B11 -> 25
A19: Sealing/consumables | B19: =Assumptions!B12 -> 5
A20: Total COGS per bag | B20: =SUM(B17:B19) -> 209.41176
A22: Contribution / Gross Profit
A23: Item | B23: ₹ / bag
A24: Net Realisation | B24: =B12 -> 373.5
A25: Less: Total COGS | B25: =-B20 -> -209.41176
A26: Gross profit per bag | B26: =B24+B25 -> 164.08824
A27: Gross margin % | B27: =B26/Assumptions!B16 -> 0.36464052
A28: Gross profit per kg roasted coffee sold | B28: =B26/(Assumptions!B7/1000) -> 656.35294
A30: Note: this is gross profit before fixed overhead (salary, biz-dev, sourcing trips, equipment depreciation) — see 'Breakeven' tab for the revenue you need to cover those.

Sheet Breakeven
A1: Breakeven — Volume & Revenue You Need to Do
A3: Answers: how much coffee do I need to sell to cover my ₹12L salary + ₹2L biz-dev draw, plus sourcing and roaster ownership costs?
A5: Fixed Cost To Cover
A6: Item | B6: Monthly | C6: Annual
A7: Owner's salary draw | B7: =Assumptions!B31 -> 100000 | C7: =B7*12 -> 1200000
A8: Business development spend | B8: =Assumptions!B32 -> 16667 | C8: =B8*12 -> 200004
A9: Green bean sourcing overhead (trips, samples) | B9: =Assumptions!B33 -> 5000 | C9: =B9*12 -> 60000
A10: Equipment depreciation (roaster + other gear) | B10: =Assumptions!B38 -> 3666.6667 | C10: =B10*12 -> 44000
A11: Other overhead (fuel, tooling, software, misc) | B11: =SUM(Assumptions!B34:B37) -> 10500 | C11: =B11*12 -> 126000
A12: Total Fixed Cost to Cover | B12: =SUM(B7:B11) -> 135833.67 | C12: =SUM(C7:C11) -> 1630004
A14: Breakeven Calculation
A15: Item | B15: Value
A16: Gross profit per bag (from Unit Economics) | B16: ='Unit Economics'!B26 -> 164.08824
A17: Bags/month to break even | B17: =B12/B16 -> 827.80869
A18: Bags/year to break even | B18: =C12/B16 -> 9933.7042
A19: Kg/month to break even | B19: =B17*(Assumptions!B7/1000) -> 206.95217
A20: Kg/year to break even | B20: =B18*(Assumptions!B7/1000) -> 2483.4261
A21: Gross Revenue/month to break even (at listed price, pre-fees) | B21: =B17*Assumptions!B16 -> 372513.91
A22: Gross Revenue/year to break even | B22: =B18*Assumptions!B16 -> 4470166.9
A24: ≈ per day (26 working days/month) | B24: =B17/26 -> 31.838796
A25: ≈ per week | B25: =B17/4.33 -> 191.17984
A27: This is the breakeven point — revenue that exactly covers your ₹14L/yr draw plus sourcing overhead and roaster depreciation. It assumes zero re-investment, taxes, or buffer for bad batches/returns; treat it as a floor, not a target.

Sheet Sensitivity
A1: Sensitivity — Annual Revenue Needed at Different Prices & Margins
A3: Shows how the annual revenue target moves if your selling price or gross margin differs from the base case on the Assumptions tab.
A5: Base case gross margin (from Unit Economics): | C5: ='Unit Economics'!B27 -> 0.36464052
A6: Base case selling price/bag (from Assumptions): | C6: =Assumptions!B16 -> 450
A7: Total annual fixed cost to cover: | C7: =Breakeven!C12 -> 1630004
A9: Annual Revenue Needed (₹) — by Price (rows) x Gross Margin (cols)
A10: Price / Bag \ Margin | B10: 35% | C10: 40% | D10: 45% | E10: 50% | F10: 55% | G10: 60%
A11: 350 | B11: =$C$7/0.35 -> 4657154.3 | C11: =$C$7/0.4 -> 4075010 | D11: =$C$7/0.45 -> 3622231.1 | E11: =$C$7/0.5 -> 3260008 | F11: =$C$7/0.55 -> 2963643.6 | G11: =$C$7/0.6 -> 2716673.3
A12: 400 | B12: =$C$7/0.35 -> 4657154.3 | C12: =$C$7/0.4 -> 4075010 | D12: =$C$7/0.45 -> 3622231.1 | E12: =$C$7/0.5 -> 3260008 | F12: =$C$7/0.55 -> 2963643.6 | G12: =$C$7/0.6 -> 2716673.3
A13: 450 | B13: =$C$7/0.35 -> 4657154.3 | C13: =$C$7/0.4 -> 4075010 | D13: =$C$7/0.45 -> 3622231.1 | E13: =$C$7/0.5 -> 3260008 | F13: =$C$7/0.55 -> 2963643.6 | G13: =$C$7/0.6 -> 2716673.3
A14: 500 | B14: =$C$7/0.35 -> 4657154.3 | C14: =$C$7/0.4 -> 4075010 | D14: =$C$7/0.45 -> 3622231.1 | E14: =$C$7/0.5 -> 3260008 | F14: =$C$7/0.55 -> 2963643.6 | G14: =$C$7/0.6 -> 2716673.3
A15: 550 | B15: =$C$7/0.35 -> 4657154.3 | C15: =$C$7/0.4 -> 4075010 | D15: =$C$7/0.45 -> 3622231.1 | E15: =$C$7/0.5 -> 3260008 | F15: =$C$7/0.55 -> 2963643.6 | G15: =$C$7/0.6 -> 2716673.3
A16: 600 | B16: =$C$7/0.35 -> 4657154.3 | C16: =$C$7/0.4 -> 4075010 | D16: =$C$7/0.45 -> 3622231.1 | E16: =$C$7/0.5 -> 3260008 | F16: =$C$7/0.55 -> 2963643.6 | G16: =$C$7/0.6 -> 2716673.3
A18: Note: this table shows total annual revenue needed regardless of bag price (revenue = fixed cost / margin) — price only matters for converting that revenue into a unit count. Use the 'Bags Needed' table below for that.
A20: Bags/Year Needed — by Price (rows) x Gross Margin (cols)
A21: Price / Bag \ Margin | B21: 35% | C21: 40% | D21: 45% | E21: 50% | F21: 55% | G21: 60%
A22: 350 | B22: =($C$7/0.35)/350 -> 13306.155 | C22: =($C$7/0.4)/350 -> 11642.886 | D22: =($C$7/0.45)/350 -> 10349.232 | E22: =($C$7/0.5)/350 -> 9314.3086 | F22: =($C$7/0.55)/350 -> 8467.5532 | G22: =($C$7/0.6)/350 -> 7761.9238
A23: 400 | B23: =($C$7/0.35)/400 -> 11642.886 | C23: =($C$7/0.4)/400 -> 10187.525 | D23: =($C$7/0.45)/400 -> 9055.5778 | E23: =($C$7/0.5)/400 -> 8150.02 | F23: =($C$7/0.55)/400 -> 7409.1091 | G23: =($C$7/0.6)/400 -> 6791.6833
A24: 450 | B24: =($C$7/0.35)/450 -> 10349.232 | C24: =($C$7/0.4)/450 -> 9055.5778 | D24: =($C$7/0.45)/450 -> 8049.4025 | E24: =($C$7/0.5)/450 -> 7244.4622 | F24: =($C$7/0.55)/450 -> 6585.8747 | G24: =($C$7/0.6)/450 -> 6037.0519
A25: 500 | B25: =($C$7/0.35)/500 -> 9314.3086 | C25: =($C$7/0.4)/500 -> 8150.02 | D25: =($C$7/0.45)/500 -> 7244.4622 | E25: =($C$7/0.5)/500 -> 6520.016 | F25: =($C$7/0.55)/500 -> 5927.2873 | G25: =($C$7/0.6)/500 -> 5433.3467
A26: 550 | B26: =($C$7/0.35)/550 -> 8467.5532 | C26: =($C$7/0.4)/550 -> 7409.1091 | D26: =($C$7/0.45)/550 -> 6585.8747 | E26: =($C$7/0.5)/550 -> 5927.2873 | F26: =($C$7/0.55)/550 -> 5388.443 | G26: =($C$7/0.6)/550 -> 4939.4061
A27: 600 | B27: =($C$7/0.35)/600 -> 7761.9238 | C27: =($C$7/0.4)/600 -> 6791.6833 | D27: =($C$7/0.45)/600 -> 6037.0519 | E27: =($C$7/0.5)/600 -> 5433.3467 | F27: =($C$7/0.55)/600 -> 4939.4061 | G27: =($C$7/0.6)/600 -> 4527.7889

Sheet Capacity vs Demand
A1: Capacity vs Demand — Can Your Roaster Actually Hit the Target?
A3: Breakeven tells you what revenue you need. This tab checks whether one person, one roaster, working out of an apartment, can physically produce it.
A5: 1. Roasting Operation Assumptions (edit the yellow cells)
A6: Item | B6: Value | C6: Unit | D6: Notes
A7: Roast cycle time per batch (roast + cool + clean + bag) | B7: 50 | C7: minutes | D7: PLACEHOLDER — includes changeover, not just roast time
A8: Hours/day you can dedicate to roasting | B8: 4 | C8: hours | D8: Solo apartment operation — remaining hours go to sourcing, packing, sales, shipping, admin
A9: Working days/month | B9: 24 | C9: days | D9: Leaves room for sourcing trips, rest, order backlog
A10: Max batches/day at these hours | B10: =FLOOR((B8*60)/B7,1) -> 4
A12: 2. Output Capacity by Roaster Batch Size
A13: Roaster Batch Size (kg green/batch) | B13: Batches/Day | C13: Roasted kg/Day | D13: Roasted kg/Month | E13: Roasted kg/Year | F13: Bags/Year (250g) | G13: Revenue Capacity/Year
A14: 1 | B14: =$B$10 -> 4 | C14: =B14*A14*(1-Assumptions!$B$10) -> 3.4 | D14: =C14*$B$9 -> 81.6 | E14: =D14*12 -> 979.2 | F14: =E14*1000/Assumptions!$B$7 -> 3916.8 | G14: =F14*Assumptions!$B$16 -> 1762560
A15: 1.5 | B15: =$B$10 -> 4 | C15: =B15*A15*(1-Assumptions!$B$10) -> 5.1 | D15: =C15*$B$9 -> 122.4 | E15: =D15*12 -> 1468.8 | F15: =E15*1000/Assumptions!$B$7 -> 5875.2 | G15: =F15*Assumptions!$B$16 -> 2643840
A16: 2 | B16: =$B$10 -> 4 | C16: =B16*A16*(1-Assumptions!$B$10) -> 6.8 | D16: =C16*$B$9 -> 163.2 | E16: =D16*12 -> 1958.4 | F16: =E16*1000/Assumptions!$B$7 -> 7833.6 | G16: =F16*Assumptions!$B$16 -> 3525120
A17: 3 | B17: =$B$10 -> 4 | C17: =B17*A17*(1-Assumptions!$B$10) -> 10.2 | D17: =C17*$B$9 -> 244.8 | E17: =D17*12 -> 2937.6 | F17: =E17*1000/Assumptions!$B$7 -> 11750.4 | G17: =F17*Assumptions!$B$16 -> 5287680
A18: 5 | B18: =$B$10 -> 4 | C18: =B18*A18*(1-Assumptions!$B$10) -> 17 | D18: =C18*$B$9 -> 408 | E18: =D18*12 -> 4896 | F18: =E18*1000/Assumptions!$B$7 -> 19584 | G18: =F18*Assumptions!$B$16 -> 8812800
A19: 10 | B19: =$B$10 -> 4 | C19: =B19*A19*(1-Assumptions!$B$10) -> 34 | D19: =C19*$B$9 -> 816 | E19: =D19*12 -> 9792 | F19: =E19*1000/Assumptions!$B$7 -> 39168 | G19: =F19*Assumptions!$B$16 -> 17625600
A20: Row for 1.5kg ≈ your current mini-batch roaster from the Assumptions tab. Batches/day is capped by your available hours, not bean weight — a bigger roaster produces more per batch at the same labour cost.
A22: 3. Capacity vs. What You Need to Hit
A23: Milestone | B23: Kg/Year Needed | C23: Smallest Roaster That Clears It
A24: Breakeven (covers ₹12L salary + ₹2L biz-dev + overhead) | B24: =Breakeven!B20 -> 2483.4261
A25: Investor-ready range — low end (1.5x breakeven) | B25: =B24*1.5 -> 3725.1391
A26: Investor-ready range — high end (2x breakeven) | B26: =B24*2 -> 4966.8521
A28: Read this against Section 2: find the smallest roaster batch size whose 'Roasted kg/Year' clears each row above. That's the minimum equipment upgrade the numbers actually require — the rest of any capex ask (helper, packing line, second roaster) is about margin of safety and growth runway, not baseline survival.

Sheet Roaster Pricing (India)
A1: Small-Batch Coffee Roaster Pricing — India Market
A3: Pulled from live supplier listings (IndiaMART/TradeIndia) in Aug 2026. B2B listed prices on these platforms are often starting points for negotiation and usually exclude GST (typically 18% extra) and freight/installation — treat these as directional, not final quotes. Get 2-3 live quotes before committing capex.
A5: Price by Batch Capacity
A6: Batch Capacity | B6: Price — Low | C6: Price — High | D6: Example / Model | E6: Source Notes
A7: 0.1 – 0.5 kg (sample/lab/hobby roaster) | B7: 62000 | C7: 100000 | D7: Lab-model stainless steel sample roaster | E7: Pilotsmith India (Coimbatore) lab roaster listed ~₹62,000; hobby/sample models generally ₹60k-1L
A8: 1 kg (specialty imported) | B8: 400000 | C8: 470000 | D8: Aillio Bullet R1 V2 (induction, Artisan-software compatible) | E8: Naru Kitchen Equipment (Mumbai) listing ₹3,99,996 + 18% GST extra ≈ ₹4.7L landed
A9: 1.5 – 2 kg (Indian-fabricated small batch) | B9: 200000 | C9: 300000 | D9: Domestic gas/electric drum roasters, semi-automatic | E9: Estimated from adjacent capacity bands (3kg/5kg domestic units below) — few direct 1.5-2kg listings found; get a live quote from Aatomize/Top Grains/local fabricators
A10: 3 kg (small roastery) | B10: 250000 | C10: 600000 | D10: Aatomize AARoasta ARST-3 (gas, Artisan-compatible, WiFi) | E10: Aatomize (Rajkot) listing ₹5,94,000 on TradeIndia for the full-featured gas model; simpler domestic 3kg units commonly quoted lower — always negotiate/compare
A11: 5 kg (growing roastery) | B11: 215000 | C11: 743000 | D11: RPM Automation 5-25kg gas roaster (low end) vs Aatomize 5kg Commercial Gas (high end) | E11: RPM Automation (Coimbatore) ₹2,15,000; Aatomize (Rajkot) ₹7,42,878 — wide spread reflects automation level and build quality
A12: 10 kg+ (scaling/wholesale) | B12: 195000 | C12: 960000 | D12: Top Grains International 10-100kg (low end) vs Aatomize Industrial roaster (high end) | E12: Top Grains International (Hassan) ₹1,95,000; Aatomize Industrial listing ₹9,58,986 — capacity range and automation drive the gap
A14: What This Means for Your Capex Line
A15: The Capacity vs Demand tab shows you need at least a 3kg roaster to clear breakeven, and closer to 5kg to sit comfortably in the investor-ready range. Realistic budget for that jump: roughly ₹2.5L-6L for a capable 3kg unit, or ₹2.2L-7.5L for 5kg, depending on brand and automation. The Assumptions tab currently models a ₹1,75,000 roaster at 1.5kg — update that cell (Assumptions!B24) once you've picked a specific model, since it flows through to your monthly depreciation and full breakeven math.
